{
  "수호자의성": {
    "룩": {
      "1": [
        {
          "name": "기본 공격",
          "target": "단일 적군",
          "detail": "공격",
          "description": "물리 공격력의 80%만큼 1회 피해."
        },
        {
          "name": "투창",
          "target": "단일 적군",
          "detail": "공격",
          "description": [
            "현재 생명력 비율을 90%로 전환",
            "물리 공격력의 275%만큼 1회 피해",
            "기절 [100% 확률] [3턴 지속]"
          ]
        },
        {
          "name": "공성 방패",
          "target": "자신",
          "detail": "버프",
          "description": [
            "받는 물리 피해량이 90% 감소",
            "1인 공격기에 받는 피해량이 70% 감소",
            "5인 공격기에 받는 피해량이 90% 감소"
          ]
        }
      ],
      "2": [
        {
          "name": "기본 공격",
          "target": "단일 적군",
          "detail": "공격",
          "description": "물리 공격력의 90%만큼 1회 피해."
        },
        {
          "name": "투창",
          "target": "단일 적군",
          "detail": "공격",
          "description": [
            "현재 생명력 비율을 80%로 전환",
            "물리 공격력의 305%만큼 1회 피해",
            "기절 [100% 확률] [3턴 지속]"
          ]
        },
        {
          "name": "공성 방패",
          "target": "자신",
          "detail": "버프",
          "description": [
            "받는 물리 피해량이 90% 감소",
            "1인 공격기에 받는 피해량이 70% 감소",
            "5인 공격기에 받는 피해량이 90% 감소"
          ]
        }
      ],
      "3": [
        {
          "name": "기본 공격",
          "target": "단일 적군",
          "detail": "공격",
          "description": "물리 공격력의 100%만큼 1회 피해."
        },
        {
          "name": "투창",
          "target": "단일 적군",
          "detail": "공격",
          "description": [
            "현재 생명력 비율을 70%로 전환",
            "물리 공격력의 340%만큼 1회 피해",
            "기절 [100% 확률] [3턴 지속]"
          ]
        },
        {
          "name": "공성 방패",
          "target": "자신",
          "detail": "버프",
          "description": [
            "받는 물리 피해량이 90% 감소",
            "1인 공격기에 받는 피해량이 70% 감소",
            "5인 공격기에 받는 피해량이 90% 감소"
          ]
        }
      ]
    },
    "챈슬러": {
      "1": [
        {
          "name": "기본 공격",
          "target": "단일 적군",
          "detail": "공격",
          "description": "물리 공격력의 80%만큼 1회 피해."
        },
        {
          "name": "분쇄",
          "target": "단일 적군",
          "detail": "공격",
          "description": [
            "현재 생명력 비율을 90%로 전환",
            "물리 공격력의 275%만큼 1회 피해",
            "기절 [100% 확률] [3턴 지속]"
          ]
        },
        {
          "name": "위압감",
          "target": "자신",
          "detail": "버프",
          "description": [
            "받는 물리 피해량이 90% 감소",
            "1인 공격기에 받는 피해량이 70% 감소",
            "5인 공격기에 받는 피해량이 90% 감소"
          ]
        }
      ],
      "2": [
        {
          "name": "기본 공격",
          "target": "단일 적군",
          "detail": "공격",
          "description": "물리 공격력의 90%만큼 1회 피해."
        },
        {
          "name": "분쇄",
          "target": "단일 적군",
          "detail": "공격",
          "description": [
            "현재 생명력 비율을 80%로 전환",
            "물리 공격력의 305%만큼 1회 피해",
            "기절 [100% 확률] [3턴 지속]"
          ]
        },
        {
          "name": "위압감",
          "target": "자신",
          "detail": "버프",
          "description": [
            "받는 물리 피해량이 90% 감소",
            "1인 공격기에 받는 피해량이 70% 감소",
            "5인 공격기에 받는 피해량이 90% 감소"
          ]
        }
      ],
      "3": [
        {
          "name": "기본 공격",
          "target": "단일 적군",
          "detail": "공격",
          "description": "물리 공격력의 100%만큼 1회 피해."
        },
        {
          "name": "분쇄",
          "target": "단일 적군",
          "detail": "공격",
          "description": [
            "현재 생명력 비율을 70%로 전환",
            "물리 공격력의 340%만큼 1회 피해",
            "기절 [100% 확률] [3턴 지속]"
          ]
        },
        {
          "name": "위압감",
          "target": "자신",
          "detail": "버프",
          "description": [
            "받는 물리 피해량이 90% 감소",
            "1인 공격기에 받는 피해량이 70% 감소",
            "5인 공격기에 받는 피해량이 90% 감소"
          ]
        }
      ]
    },
    "루디": {
      "3": [
        {
          "name": "기본 공격",
          "target": "단일 적군",
          "detail": "공격",
          "description": "물리 공격력의 120%만큼 1회 피해."
        },
        {
          "name": "돌격",
          "target": "적군 3명",
          "detail": "공격",
          "description": [
            "물리 공격력의 220%만큼 1회 피해",
            "기절 [100% 확률] [3턴 지속]"
          ]
        },
        {
          "name": "방어준비",
          "target": "모든 아군",
          "detail": "버프",
          "description": [
            "링크 [5턴 지속]",
            "시전자 방어력의 10,000%만큼 보호막 [5턴 지속]"
          ]
        },
        {
          "name": "견고한 방패",
          "target": "자신",
          "detail": "버프",
          "description": [
            "받는 물리 피해량이 90% 감소",
            "1인 공격기에 받는 피해량이 70% 감소",
            "5인 공격기에 받는 피해량이 90% 감소",
            "30턴 후 광폭화"
          ]
        }
      ]
    }
  },
  "포디나의성": {
    "룩": {
      "1": [
        {
          "name": "기본 공격",
          "target": "단일 적군",
          "detail": "공격",
          "description": "물리 공격력의 80%만큼 1회 피해."
        },
        {
          "name": "투창",
          "target": "단일 적군",
          "detail": "공격",
          "description": [
            "물리 공격력의 275%만큼 1회 피해",
            "감전 [100% 확률] [3턴 지속]"
          ]
        },
        {
          "name": "공성 방패",
          "target": "자신",
          "detail": "버프",
          "description": [
            "받는 물리 피해량이 90% 감소",
            "1인 공격기에 받는 피해량이 70% 감소",
            "5인 공격기에 받는 피해량이 90% 감소"
          ]
        }
      ],
      "2": [
        {
          "name": "기본 공격",
          "target": "단일 적군",
          "detail": "공격",
          "description": "물리 공격력의 90%만큼 1회 피해."
        },
        {
          "name": "투창",
          "target": "단일 적군",
          "detail": "공격",
          "description": [
            "물리 공격력의 305%만큼 1회 피해",
            "감전 [100% 확률] [3턴 지속]"
          ]
        },
        {
          "name": "공성 방패",
          "target": "자신",
          "detail": "버프",
          "description": [
            "받는 물리 피해량이 90% 감소",
            "1인 공격기에 받는 피해량이 70% 감소",
            "5인 공격기에 받는 피해량이 90% 감소"
          ]
        }
      ],
      "3": [
        {
          "name": "기본 공격",
          "target": "단일 적군",
          "detail": "공격",
          "description": "물리 공격력의 100%만큼 1회 피해."
        },
        {
          "name": "투창",
          "target": "단일 적군",
          "detail": "공격",
          "description": [
            "물리 공격력의 340%만큼 1회 피해",
            "감전 [100% 확률] [3턴 지속]",
            "모든 피해 면역 [2턴 지속]"
          ]
        },
        {
          "name": "공성 방패",
          "target": "자신",
          "detail": "버프",
          "description": [
            "받는 물리 피해량이 90% 감소",
            "1인 공격기에 받는 피해량이 70% 감소",
            "5인 공격기에 받는 피해량이 90% 감소"
          ]
        }
      ]
    },
    "챈슬러": {
      "1": [
        {
          "name": "기본 공격",
          "target": "단일 적군",
          "detail": "공격",
          "description": "물리 공격력의 80%만큼 1회 피해."
        },
        {
          "name": "분쇄",
          "target": "단일 적군",
          "detail": "공격",
          "description": [
            "물리 공격력의 275%만큼 1회 피해",
            "감전 [100% 확률] [3턴 지속]"
          ]
        },
        {
          "name": "위압감",
          "target": "자신",
          "detail": "버프",
          "description": [
            "받는 물리 피해량이 90% 감소",
            "1인 공격기에 받는 피해량이 70% 감소",
            "5인 공격기에 받는 피해량이 90% 감소"
          ]
        }
      ],
      "2": [
        {
          "name": "기본 공격",
          "target": "단일 적군",
          "detail": "공격",
          "description": "물리 공격력의 90%만큼 1회 피해."
        },
        {
          "name": "분쇄",
          "target": "단일 적군",
          "detail": "공격",
          "description": [
            "물리 공격력의 305%만큼 1회 피해",
            "감전 [100% 확률] [3턴 지속]"
          ]
        },
        {
          "name": "위압감",
          "target": "자신",
          "detail": "버프",
          "description": [
            "받는 물리 피해량이 90% 감소",
            "1인 공격기에 받는 피해량이 70% 감소",
            "5인 공격기에 받는 피해량이 90% 감소"
          ]
        }
      ],
      "3": [
        {
          "name": "기본 공격",
          "target": "단일 적군",
          "detail": "공격",
          "description": "물리 공격력의 100%만큼 1회 피해."
        },
        {
          "name": "분쇄",
          "target": "단일 적군",
          "detail": "공격",
          "description": [
            "물리 공격력의 340%만큼 1회 피해",
            "감전 [100% 확률] [3턴 지속]"
          ]
        },
        {
          "name": "위압감",
          "target": "자신",
          "detail": "버프",
          "description": [
            "받는 물리 피해량이 90% 감소",
            "1인 공격기에 받는 피해량이 70% 감소",
            "5인 공격기에 받는 피해량이 90% 감소"
          ]
        }
      ]
    },
    "아일린": {
      "3": [
        {
          "name": "기본 공격",
          "target": "단일 적군",
          "detail": "공격",
          "description": [
            "물리 공격력의 120%만큼 1회 피해",
            "대상이 [감전] 상태일 경우 물리 공격력의 75%만큼 추가 피해"
          ]
        },
        {
          "name": "뇌제의 분노",
          "target": "적군 3명",
          "detail": "공격",
          "description": [
            "물리 공격력의 80%만큼 3회 관통 피해",
            "각 공격마다 감전 [100% 확률] [3턴 지속]"
          ]
        },
        {
          "name": "청천병력",
          "target": "모든 적군",
          "detail": "공격",
          "description": [
            "물리 공격력의 80%만큼 2회 관통 피해",
            "각 공격마다 감전 [100% 확률] [3턴 지속]"
          ]
        },
        {
          "name": "포디나의 분노",
          "target": "자신",
          "detail": "버프",
          "description": [
            "받는 물리 피해량이 90% 감소",
            "1인 공격기에 받는 피해량이 70% 감소",
            "5인 공격기에 받는 피해량이 90% 감소",
            "30턴 후 광폭화"
          ]
        }
      ]
    }
  },
  "불멸의성": {
    "룩": {
      "1": [
        {
          "name": "기본 공격",
          "target": "단일 적군",
          "detail": "공격",
          "description": "물리 공격력의 80%만큼 1회 피해."
        },
        {
          "name": "투창",
          "target": "단일 적군",
          "detail": "공격",
          "description": [
            "물리 공격력의 275%만큼 1회 피해",
            "화상 [100% 확률] [3턴 지속]"
          ]
        },
        {
          "name": "공성 방패",
          "target": "자신",
          "detail": "버프",
          "description": [
            "받는 물리 피해량이 90% 감소",
            "1인 공격기에 받는 피해량이 70% 감소",
            "5인 공격기에 받는 피해량이 90% 감소"
          ]
        }
      ],
      "2": [
        {
          "name": "기본 공격",
          "target": "단일 적군",
          "detail": "공격",
          "description": "물리 공격력의 90%만큼 1회 피해."
        },
        {
          "name": "투창",
          "target": "단일 적군",
          "detail": "공격",
          "description": [
            "물리 공격력의 305%만큼 1회 피해",
            "화상 [100% 확률] [3턴 지속]"
          ]
        },
        {
          "name": "공성 방패",
          "target": "자신",
          "detail": "버프",
          "description": [
            "받는 물리 피해량이 90% 감소",
            "1인 공격기에 받는 피해량이 70% 감소",
            "5인 공격기에 받는 피해량이 90% 감소"
          ]
        }
      ],
      "3": [
        {
          "name": "기본 공격",
          "target": "단일 적군",
          "detail": "공격",
          "description": "물리 공격력의 100%만큼 1회 피해."
        },
        {
          "name": "투창",
          "target": "단일 적군",
          "detail": "공격",
          "description": [
            "물리 공격력의 340%만큼 1회 피해",
            "화상 [100% 확률] [3턴 지속]"
          ]
        },
        {
          "name": "공성 방패",
          "target": "자신",
          "detail": "버프",
          "description": [
            "받는 물리 피해량이 90% 감소",
            "1인 공격기에 받는 피해량이 70% 감소",
            "5인 공격기에 받는 피해량이 90% 감소"
          ]
        }
      ]
    },
    "챈슬러": {
      "1": [
        {
          "name": "기본 공격",
          "target": "단일 적군",
          "detail": "공격",
          "description": "물리 공격력의 80%만큼 1회 피해."
        },
        {
          "name": "분쇄",
          "target": "단일 적군",
          "detail": "공격",
          "description": [
            "물리 공격력의 275%만큼 1회 피해",
            "화상 [100% 확률] [3턴 지속]"
          ]
        },
        {
          "name": "위압감",
          "target": "자신",
          "detail": "버프",
          "description": [
            "받는 물리 피해량이 90% 감소",
            "1인 공격기에 받는 피해량이 70% 감소",
            "5인 공격기에 받는 피해량이 90% 감소"
          ]
        }
      ],
      "2": [
        {
          "name": "기본 공격",
          "target": "단일 적군",
          "detail": "공격",
          "description": "물리 공격력의 90%만큼 1회 피해."
        },
        {
          "name": "분쇄",
          "target": "단일 적군",
          "detail": "공격",
          "description": [
            "물리 공격력의 305%만큼 1회 피해",
            "화상 [100% 확률] [3턴 지속]"
          ]
        },
        {
          "name": "위압감",
          "target": "자신",
          "detail": "버프",
          "description": [
            "받는 물리 피해량이 90% 감소",
            "1인 공격기에 받는 피해량이 70% 감소",
            "5인 공격기에 받는 피해량이 90% 감소"
          ]
        }
      ],
      "3": [
        {
          "name": "기본 공격",
          "target": "단일 적군",
          "detail": "공격",
          "description": "물리 공격력의 100%만큼 1회 피해."
        },
        {
          "name": "분쇄",
          "target": "단일 적군",
          "detail": "공격",
          "description": [
            "물리 공격력의 340%만큼 1회 피해",
            "화상 [100% 확률] [3턴 지속]"
          ]
        },
        {
          "name": "위압감",
          "target": "자신",
          "detail": "버프",
          "description": [
            "받는 물리 피해량이 90% 감소",
            "1인 공격기에 받는 피해량이 70% 감소",
            "5인 공격기에 받는 피해량이 90% 감소"
          ]
        }
      ]
    },
    "레이첼": {
      "3": [
        {
          "name": "기본 공격",
          "target": "단일 적군",
          "detail": "공격",
          "description": [
            "물리 공격력의 120%만큼 1회 피해",
            "화상 [100% 확률] [2턴 지속]"
          ]
        },
        {
          "name": "염화",
          "target": "적군 3명",
          "detail": "공격",
          "description": "물리 공격력의 120%만큼 2회 피해"
        },
        {
          "name": "불새",
          "target": "모든 적군",
          "detail": "공격",
          "description": [
            "물리 공격력의 160%만큼 1회 피해",
            "방어력 감소 36% [100% 확률] [5턴 지속]",
            "모든 공격력 감소 [100% 확률] [5턴 지속]"
          ]
        },
        [
          {
            "name": "화염의 힘",
            "target": "자신",
            "detail": "버프",
            "description": [
              "받는 물리 피해량이 90% 감소",
              "1인 공격기에 받는 피해량이 70% 감소",
              "5인 공격기에 받는 피해량이 90% 감소",
              "30턴 후 광폭화"
            ]
          },
          {
            "target": "적군 3명",
            "detail": "공격",
            "description": "자신이 피격 1회 후 화상 [100% 확률] [2턴 지속]"
          }
        ]
      ]
    }
  },
  "죽음의성": {
    "룩": {
      "1": [
        {
          "name": "기본 공격",
          "target": "단일 적군",
          "detail": "공격",
          "description": "물리 공격력의 80%만큼 1회 피해."
        },
        {
          "name": "투창",
          "target": "단일 적군",
          "detail": "공격",
          "description": [
            "물리 공격력의 275%만큼 1회 피해",
            "침묵 [100% 확률] [3턴 지속]"
          ]
        },
        {
          "name": "공성 방패",
          "target": "자신",
          "detail": "버프",
          "description": [
            "받는 마법 피해량이 90% 감소",
            "1인 공격기에 받는 피해량이 70% 감소",
            "5인 공격기에 받는 피해량이 90% 감소"
          ]
        }
      ],
      "2": [
        {
          "name": "기본 공격",
          "target": "단일 적군",
          "detail": "공격",
          "description": "물리 공격력의 90%만큼 1회 피해."
        },
        {
          "name": "투창",
          "target": "단일 적군",
          "detail": "공격",
          "description": [
            "물리 공격력의 305%만큼 1회 피해",
            "침묵 [100% 확률] [3턴 지속]"
          ]
        },
        {
          "name": "공성 방패",
          "target": "자신",
          "detail": "버프",
          "description": [
            "받는 마법 피해량이 90% 감소",
            "1인 공격기에 받는 피해량이 70% 감소",
            "5인 공격기에 받는 피해량이 90% 감소"
          ]
        }
      ],
      "3": [
        {
          "name": "기본 공격",
          "target": "단일 적군",
          "detail": "공격",
          "description": "물리 공격력의 100%만큼 1회 피해."
        },
        {
          "name": "투창",
          "target": "단일 적군",
          "detail": "공격",
          "description": [
            "물리 공격력의 340%만큼 1회 피해",
            "침묵 [100% 확률] [3턴 지속]"
          ]
        },
        {
          "name": "공성 방패",
          "target": "자신",
          "detail": "버프",
          "description": [
            "받는 마법 피해량이 90% 감소",
            "1인 공격기에 받는 피해량이 70% 감소",
            "5인 공격기에 받는 피해량이 90% 감소"
          ]
        }
      ]
    },
    "챈슬러": {
      "1": [
        {
          "name": "기본 공격",
          "target": "단일 적군",
          "detail": "공격",
          "description": "물리 공격력의 80%만큼 1회 피해."
        },
        {
          "name": "분쇄",
          "target": "단일 적군",
          "detail": "공격",
          "description": [
            "물리 공격력의 275%만큼 1회 피해",
            "침묵 [100% 확률] [3턴 지속]"
          ]
        },
        {
          "name": "위압감",
          "target": "자신",
          "detail": "버프",
          "description": [
            "받는 마법 피해량이 90% 감소",
            "1인 공격기에 받는 피해량이 70% 감소",
            "5인 공격기에 받는 피해량이 90% 감소"
          ]
        }
      ],
      "2": [
        {
          "name": "기본 공격",
          "target": "단일 적군",
          "detail": "공격",
          "description": "물리 공격력의 90%만큼 1회 피해."
        },
        {
          "name": "분쇄",
          "target": "단일 적군",
          "detail": "공격",
          "description": [
            "물리 공격력의 305%만큼 1회 피해",
            "화상 [100% 확률] [3턴 지속]"
          ]
        },
        {
          "name": "위압감",
          "target": "자신",
          "detail": "버프",
          "description": [
            "받는 마법 피해량이 90% 감소",
            "1인 공격기에 받는 피해량이 70% 감소",
            "5인 공격기에 받는 피해량이 90% 감소"
          ]
        }
      ],
      "3": [
        {
          "name": "기본 공격",
          "target": "단일 적군",
          "detail": "공격",
          "description": "물리 공격력의 100%만큼 1회 피해."
        },
        {
          "name": "분쇄",
          "target": "단일 적군",
          "detail": "공격",
          "description": [
            "물리 공격력의 340%만큼 1회 피해",
            "침묵 [100% 확률] [3턴 지속]"
          ]
        },
        {
          "name": "위압감",
          "target": "자신",
          "detail": "버프",
          "description": [
            "받는 마법 피해량이 90% 감소",
            "1인 공격기에 받는 피해량이 70% 감소",
            "5인 공격기에 받는 피해량이 90% 감소"
          ]
        }
      ]
    },
    "델론즈": {
      "3": [
        {
          "name": "기본 공격",
          "target": "단일 적군",
          "detail": "공격",
          "description": [
            "물리 공격력의 120%만큼 1회 피해",
            "침묵 [100% 확률] [1턴 지속]"
          ]
        },
        {
          "name": "사신강림",
          "target": "모든 적군",
          "detail": "공격",
          "description": [
            "물리 공격력의 170%만큼 1회 피해",
            "침묵 [100% 확률] [4턴 지속]"
          ]
        },
        {
          "name": "죽음의 일격",
          "target": "단일 적군",
          "detail": "공격",
          "description": [
            "물리 공격력의 300%만큼 5회 피해",
            "해당 스킬의 직접 피해로 적군 처치 시 100% 위력으로 연속 발동"
          ]
        },
        {
          "name": "죽음의 경계",
          "target": "자신",
          "detail": "버프",
          "description": [
            "받는 마법 피해량이 90% 감소",
            "1인 공격기에 받는 피해량이 70% 감소",
            "5인 공격기에 받는 피해량이 90% 감소",
            "30턴 후 광폭화",
            "적군 사망 후 모든 피해 무효화 [피격 4회]"
          ]
        }
      ]
    }
  },
  "고대용의성": {
    "룩": {
      "1": [
        {
          "name": "기본 공격",
          "target": "단일 적군",
          "detail": "공격",
          "description": "물리 공격력의 80%만큼 1회 피해."
        },
        {
          "name": "투창",
          "target": "단일 적군",
          "detail": "공격",
          "description": [
            "물리 공격력의 275%만큼 1회 피해",
            "기절 [100% 확률] [3턴 지속]"
          ]
        },
        {
          "name": "공성 방패",
          "target": "자신",
          "detail": "버프",
          "description": [
            "받는 마법 피해량이 90% 감소",
            "1인 공격기에 받는 피해량이 70% 감소",
            "5인 공격기에 받는 피해량이 90% 감소"
          ]
        }
      ],
      "2": [
        {
          "name": "기본 공격",
          "target": "단일 적군",
          "detail": "공격",
          "description": "물리 공격력의 90%만큼 1회 피해."
        },
        {
          "name": "투창",
          "target": "단일 적군",
          "detail": "공격",
          "description": [
            "물리 공격력의 305%만큼 1회 피해",
            "기절 [100% 확률] [3턴 지속]"
          ]
        },
        {
          "name": "공성 방패",
          "target": "자신",
          "detail": "버프",
          "description": [
            "받는 마법 피해량이 90% 감소",
            "1인 공격기에 받는 피해량이 70% 감소",
            "5인 공격기에 받는 피해량이 90% 감소"
          ]
        }
      ],
      "3": [
        {
          "name": "기본 공격",
          "target": "단일 적군",
          "detail": "공격",
          "description": "물리 공격력의 100%만큼 1회 피해."
        },
        {
          "name": "투창",
          "target": "단일 적군",
          "detail": "공격",
          "description": [
            "물리 공격력의 340%만큼 1회 피해",
            "기절 [100% 확률] [3턴 지속]"
          ]
        },
        {
          "name": "공성 방패",
          "target": "자신",
          "detail": "버프",
          "description": [
            "받는 마법 피해량이 90% 감소",
            "1인 공격기에 받는 피해량이 70% 감소",
            "5인 공격기에 받는 피해량이 90% 감소"
          ]
        }
      ]
    },
    "챈슬러": {
      "1": [
        {
          "name": "기본 공격",
          "target": "단일 적군",
          "detail": "공격",
          "description": "물리 공격력의 80%만큼 1회 피해."
        },
        {
          "name": "분쇄",
          "target": "단일 적군",
          "detail": "공격",
          "description": [
            "물리 공격력의 275%만큼 1회 피해",
            "용염 [100% 확률] [3턴 지속]"
          ]
        },
        {
          "name": "위압감",
          "target": "자신",
          "detail": "버프",
          "description": [
            "받는 마법 피해량이 90% 감소",
            "1인 공격기에 받는 피해량이 70% 감소",
            "5인 공격기에 받는 피해량이 90% 감소"
          ]
        }
      ],
      "2": [
        {
          "name": "기본 공격",
          "target": "단일 적군",
          "detail": "공격",
          "description": "물리 공격력의 90%만큼 1회 피해."
        },
        {
          "name": "분쇄",
          "target": "단일 적군",
          "detail": "공격",
          "description": [
            "물리 공격력의 305%만큼 1회 피해",
            "용염 [100% 확률] [3턴 지속]"
          ]
        },
        {
          "name": "위압감",
          "target": "자신",
          "detail": "버프",
          "description": [
            "받는 마법 피해량이 90% 감소",
            "1인 공격기에 받는 피해량이 70% 감소",
            "5인 공격기에 받는 피해량이 90% 감소"
          ]
        }
      ],
      "3": [
        {
          "name": "기본 공격",
          "target": "단일 적군",
          "detail": "공격",
          "description": "물리 공격력의 100%만큼 1회 피해."
        },
        {
          "name": "분쇄",
          "target": "단일 적군",
          "detail": "공격",
          "description": [
            "물리 공격력의 340%만큼 1회 피해",
            "용염 [100% 확률] [3턴 지속]"
          ]
        },
        {
          "name": "위압감",
          "target": "자신",
          "detail": "버프",
          "description": [
            "받는 마법 피해량이 90% 감소",
            "1인 공격기에 받는 피해량이 70% 감소",
            "5인 공격기에 받는 피해량이 90% 감소"
          ]
        }
      ]
    },
    "제이브": {
      "3": [
        {
          "name": "기본 공격",
          "target": "단일 적군",
          "detail": "공격",
          "description": [
            "물리 공격력의 120%만큼 1회 피해",
            "용염 [100% 확률] [2턴 지속]"
          ]
        },
        {
          "name": "분노의 일격",
          "target": "모든 적군",
          "detail": "공격",
          "description": [
            "물리 공격력의 120%만큼 1회 피해",
            "피해 대상이 1명 줄어들 떄마다 15%만큼 피해량 증가",
            "기절 [100% 확률] [2턴 지속]"
          ]
        },
        {
          "name": "용의 분노",
          "target": "모든 적군",
          "detail": "공격",
          "description": [
            "물리 공격력의 55%만큼 2회 관통 피해",
            "피해 대상이 1명 줄어들 떄마다 8%만큼 피해량 증가",
            "용염 [100% 확률] [2턴 지속]"
          ]
        },
        [
          {
            "name": "복수의 갑옷",
            "target": "자신",
            "detail": "버프",
            "description": [
              "받는 마법 피해량이 90% 감소",
              "1인 공격기에 받는 피해량이 70% 감소",
              "5인 공격기에 받는 피해량이 90% 감소",
              "반격 [25% 확률]",
              "30턴 후 광폭화"
            ]
          },
          {
            "target": "반격 발동 시 적군 3명",
            "detail": "공격",
            "description": [
              "물리 공격력의 60%만큼 1회 피해 [치명타 확률 100%, 치명타 피해 500% 추가 적용]",
              "용염 [100% 확률] [2턴 지속]"
            ]
          }
        ]
      ]
    }
  },
  "혹한의성": {
    "룩": {
      "1": [
        {
          "name": "기본 공격",
          "target": "단일 적군",
          "detail": "공격",
          "description": "물리 공격력의 80%만큼 1회 피해."
        },
        {
          "name": "투창",
          "target": "단일 적군",
          "detail": "공격",
          "description": [
            "물리 공격력의 275%만큼 1회 피해",
            "빙결 [100% 확률] [3턴 지속]"
          ]
        },
        {
          "name": "공성 방패",
          "target": "자신",
          "detail": "버프",
          "description": [
            "받는 마법 피해량이 90% 감소",
            "1인 공격기에 받는 피해량이 70% 감소",
            "5인 공격기에 받는 피해량이 90% 감소"
          ]
        }
      ],
      "2": [
        {
          "name": "기본 공격",
          "target": "단일 적군",
          "detail": "공격",
          "description": "물리 공격력의 90%만큼 1회 피해."
        },
        {
          "name": "투창",
          "target": "단일 적군",
          "detail": "공격",
          "description": [
            "물리 공격력의 305%만큼 1회 피해",
            "빙결 [100% 확률] [3턴 지속]"
          ]
        },
        {
          "name": "공성 방패",
          "target": "자신",
          "detail": "버프",
          "description": [
            "받는 마법 피해량이 90% 감소",
            "1인 공격기에 받는 피해량이 70% 감소",
            "5인 공격기에 받는 피해량이 90% 감소"
          ]
        }
      ],
      "3": [
        {
          "name": "기본 공격",
          "target": "단일 적군",
          "detail": "공격",
          "description": "물리 공격력의 100%만큼 1회 피해."
        },
        {
          "name": "투창",
          "target": "단일 적군",
          "detail": "공격",
          "description": [
            "물리 공격력의 340%만큼 1회 피해",
            "빙결 [100% 확률] [3턴 지속]"
          ]
        },
        {
          "name": "공성 방패",
          "target": "자신",
          "detail": "버프",
          "description": [
            "받는 마법 피해량이 90% 감소",
            "1인 공격기에 받는 피해량이 70% 감소",
            "5인 공격기에 받는 피해량이 90% 감소"
          ]
        }
      ]
    },
    "챈슬러": {
      "1": [
        {
          "name": "기본 공격",
          "target": "단일 적군",
          "detail": "공격",
          "description": "물리 공격력의 80%만큼 1회 피해."
        },
        {
          "name": "분쇄",
          "target": "단일 적군",
          "detail": "공격",
          "description": [
            "물리 공격력의 275%만큼 1회 피해",
            "빙결 [100% 확률] [3턴 지속]"
          ]
        },
        {
          "name": "위압감",
          "target": "자신",
          "detail": "버프",
          "description": [
            "받는 마법 피해량이 90% 감소",
            "1인 공격기에 받는 피해량이 70% 감소",
            "5인 공격기에 받는 피해량이 90% 감소"
          ]
        }
      ],
      "2": [
        {
          "name": "기본 공격",
          "target": "단일 적군",
          "detail": "공격",
          "description": "물리 공격력의 90%만큼 1회 피해."
        },
        {
          "name": "분쇄",
          "target": "단일 적군",
          "detail": "공격",
          "description": [
            "물리 공격력의 305%만큼 1회 피해",
            "빙결 [100% 확률] [3턴 지속]"
          ]
        },
        {
          "name": "위압감",
          "target": "자신",
          "detail": "버프",
          "description": [
            "받는 마법 피해량이 90% 감소",
            "1인 공격기에 받는 피해량이 70% 감소",
            "5인 공격기에 받는 피해량이 90% 감소"
          ]
        }
      ],
      "3": [
        {
          "name": "기본 공격",
          "target": "단일 적군",
          "detail": "공격",
          "description": "물리 공격력의 100%만큼 1회 피해."
        },
        [
          {
            "name": "분쇄",
            "target": "단일 적군",
            "detail": "공격",
            "description": [
              "물리 공격력의 340%만큼 1회 피해",
              "빙결 [100% 확률] [3턴 지속]"
            ]
          },
          {
            "target": "공격력이 가장 높은 아군",
            "detail": "버프",
            "description": ["혹한의 기운 [5턴 지속]", "혹한의 숨결 [5턴 지속]"]
          }
        ],
        {
          "name": "위압감",
          "target": "자신",
          "detail": "버프",
          "description": [
            "받는 마법 피해량이 90% 감소",
            "1인 공격기에 받는 피해량이 70% 감소",
            "5인 공격기에 받는 피해량이 90% 감소"
          ]
        }
      ]
    },
    "스파이크": {
      "3": [
        {
          "name": "기본 공격",
          "target": "단일 적군",
          "detail": "공격",
          "description": "물리 공격력의 120%만큼 1회 피해"
        },
        [
          {
            "name": "혹한의 일격",
            "target": "단일 적군",
            "detail": "공격",
            "description": [
              "물리 공격력의 195%만큼 1회 피해",
              "빙결 [100% 확률] [3턴 지속]",
              "혹한의 기운 보유 시 [치명타 확률 100%로 적용]",
              "혹한의 숨결 보유 시 [치명타 피해 500%로 추가 적용]"
            ]
          },
          {
            "target": "주 스킬 대상과 동일 열 적군",
            "detail": "공격",
            "description": [
              "물리 공격력의 75%만큼 1회 피해",
              "빙결 [100% 확률] [3턴 지속]",
              "혹한의 기운 보유 시 [치명타 확률 100%로 적용]",
              "혹한의 숨결 보유 시 [치명타 피해 500%로 추가 적용]"
            ]
          }
        ],
        {
          "name": "혹한의 지진",
          "target": "모든 적군",
          "detail": "공격",
          "description": [
            "물리 공격력의 80%만큼 2회 피해",
            "각 공격마다 빙결 [100% 확률] [2턴 지속]",
            "혹한의 기운 보유 시 [치명타 확률 100%로 적용]",
            "혹한의 숨결 보유 시 [치명타 피해 500%로 추가 적용]"
          ]
        },
        {
          "name": "혹한의 심장",
          "target": "자신",
          "detail": "버프",
          "description": [
            "받는 마법 피해량이 90% 감소",
            "1인 공격기에 받는 피해량이 70% 감소",
            "5인 공격기에 받는 피해량이 90% 감소",
            "30턴 후 광폭화"
          ]
        }
      ]
    }
  },
  "지옥의성": {
    "룩": {
      "1": [
        {
          "name": "기본 공격",
          "target": "단일 적군",
          "detail": "공격",
          "description": "물리 공격력의 80%만큼 1회 피해."
        },
        {
          "name": "투창",
          "target": "단일 적군",
          "detail": "공격",
          "description": [
            "물리 공격력의 275%만큼 1회 피해",
            "즉사 [100% 확률] [3턴 지속]"
          ]
        },
        {
          "name": "공성 방패",
          "target": "자신",
          "detail": "버프",
          "description": [
            "5인 공격기에 받는 피해량이 90% 감소",
            "피격 후 스킬 쿨타임 감소 15초"
          ]
        }
      ],
      "2": [
        {
          "name": "기본 공격",
          "target": "단일 적군",
          "detail": "공격",
          "description": "물리 공격력의 90%만큼 1회 피해."
        },
        {
          "name": "투창",
          "target": "단일 적군",
          "detail": "공격",
          "description": [
            "물리 공격력의 305%만큼 1회 피해",
            "즉사 [100% 확률] [3턴 지속]"
          ]
        },
        {
          "name": "공성 방패",
          "target": "자신",
          "detail": "버프",
          "description": [
            "5인 공격기에 받는 피해량이 90% 감소",
            "피격 후 스킬 쿨타임 감소 15초"
          ]
        }
      ],
      "3": [
        {
          "name": "기본 공격",
          "target": "단일 적군",
          "detail": "공격",
          "description": "물리 공격력의 100%만큼 1회 피해."
        },
        {
          "name": "투창",
          "target": "단일 적군",
          "detail": "공격",
          "description": [
            "물리 공격력의 340%만큼 1회 피해",
            "즉사 [100% 확률] [3턴 지속]"
          ]
        },
        {
          "name": "공성 방패",
          "target": "자신",
          "detail": "버프",
          "description": [
            "5인 공격기에 받는 피해량이 90% 감소",
            "받는 모든 피해가 크게 감소",
            "피격 후 스킬 쿨타임 감소 15초"
          ]
        }
      ]
    },
    "챈슬러": {
      "1": [
        {
          "name": "기본 공격",
          "target": "단일 적군",
          "detail": "공격",
          "description": "물리 공격력의 80%만큼 1회 피해."
        },
        {
          "name": "분쇄",
          "target": "단일 적군",
          "detail": "공격",
          "description": [
            "물리 공격력의 275%만큼 1회 피해",
            "즉사 [100% 확률] [3턴 지속]"
          ]
        },
        {
          "name": "위압감",
          "target": "자신",
          "detail": "버프",
          "description": [
            "5인 공격기에 받는 피해량이 90% 감소",
            "피격 후 스킬 쿨타임 감소 15초"
          ]
        }
      ],
      "2": [
        {
          "name": "기본 공격",
          "target": "단일 적군",
          "detail": "공격",
          "description": "물리 공격력의 90%만큼 1회 피해."
        },
        {
          "name": "분쇄",
          "target": "단일 적군",
          "detail": "공격",
          "description": [
            "물리 공격력의 305%만큼 1회 피해",
            "즉사 [100% 확률] [3턴 지속]"
          ]
        },
        {
          "name": "위압감",
          "target": "자신",
          "detail": "버프",
          "description": [
            "5인 공격기에 받는 피해량이 90% 감소",
            "피격 후 스킬 쿨타임 감소 15초"
          ]
        }
      ],
      "3": [
        {
          "name": "기본 공격",
          "target": "단일 적군",
          "detail": "공격",
          "description": "물리 공격력의 100%만큼 1회 피해."
        },
        {
          "name": "분쇄",
          "target": "단일 적군",
          "detail": "공격",
          "description": [
            "물리 공격력의 340%만큼 1회 피해",
            "즉사 [100% 확률] [3턴 지속]"
          ]
        },
        {
          "name": "위압감",
          "target": "자신",
          "detail": "버프",
          "description": [
            "5인 공격기에 받는 피해량이 90% 감소",
            "받는 모든 피해가 크게 감소",
            "피격 후 스킬 쿨타임 감소 15초"
          ]
        }
      ]
    },
    "크리스": {
      "3": [
        {
          "name": "기본 공격",
          "target": "단일 적군",
          "detail": "공격",
          "description": [
            "물리 공격력의 120%만큼 1회 피해",
            "즉사 [100% 확률] [3턴 지속]"
          ]
        },
        {
          "name": "어둠의 일격",
          "target": "단일 적군",
          "detail": "공격",
          "description": [
            "물리 공격력의 300%만큼 1회 피해",
            "즉사 [100% 확률] [3턴 지속]",
            "즉사 [100% 확률] [3턴 지속]"
          ]
        },
        {
          "name": "어둠의 속삭임",
          "target": "모든 적군",
          "detail": "공격",
          "description": [
            "물리 공격력의 160%만큼 1회 피해",
            "즉사 [100% 확률] [3턴 지속]"
          ]
        },
        {
          "name": "혹한의 심장",
          "target": "자신",
          "detail": "버프",
          "description": [
            "5인 공격기에 받는 피해량이 90% 감소",
            "30턴 후 광폭화"
          ]
        }
      ]
    }
  }
}
